fairseq/__init__.py
fairseq/binarizer.py
fairseq/bleu.py
fairseq/checkpoint_utils.py
fairseq/distributed_utils.py
fairseq/fb_hub.py
fairseq/file_utils.py
fairseq/hub_utils.py
fairseq/legacy_distributed_data_parallel.py
fairseq/meters.py
fairseq/options.py
fairseq/pdb.py
fairseq/progress_bar.py
fairseq/pybleu.py
fairseq/registry.py
fairseq/search.py
fairseq/sequence_generator.py
fairseq/sequence_scorer.py
fairseq/tokenizer.py
fairseq/trainer.py
fairseq/utils.py
fairseq/criterions/__init__.py
fairseq/criterions/cross_entropy.py
fairseq/criterions/fairseq_criterion.py
fairseq/criterions/label_smoothed_cross_entropy.py
fairseq/criterions/label_smoothed_length_cross_entropy.py
fairseq/data/__init__.py
fairseq/data/base_wrapper_dataset.py
fairseq/data/concat_dataset.py
fairseq/data/data_utils.py
fairseq/data/dictionary.py
fairseq/data/fairseq_dataset.py
fairseq/data/indexed_dataset.py
fairseq/data/iterators.py
fairseq/data/language_pair_dataset.py
fairseq/data/language_pair_self_dataset_mask.py
fairseq/data/prepend_token_dataset.py
fairseq/data/encoders/__init__.py
fairseq/data/encoders/gpt2_bpe.py
fairseq/data/encoders/moses_tokenizer.py
fairseq/data/encoders/nltk_tokenizer.py
fairseq/data/encoders/sentencepiece_bpe.py
fairseq/data/encoders/space_tokenizer.py
fairseq/data/encoders/subword_nmt_bpe.py
fairseq/fb_tbmf_wrapper/__init__.py
fairseq/models/__init__.py
fairseq/models/bert_seq2seq.py
fairseq/models/composite_encoder.py
fairseq/models/distributed_fairseq_model.py
fairseq/models/fairseq_decoder.py
fairseq/models/fairseq_encoder.py
fairseq/models/fairseq_incremental_decoder.py
fairseq/models/fairseq_model.py
fairseq/models/transformer.py
fairseq/modules/__init__.py
fairseq/modules/adaptive_input.py
fairseq/modules/adaptive_softmax.py
fairseq/modules/beamable_mm.py
fairseq/modules/character_token_embedder.py
fairseq/modules/conv_tbc.py
fairseq/modules/downsampled_multihead_attention.py
fairseq/modules/dynamic_convolution.py
taskbots-0.1.0.dist-info/LICENSE
taskbots-0.1.0.dist-info/METADATA
taskbots-0.1.0.dist-info/WHEEL
taskbots-0.1.0.dist-info/top_level.txt
taskbots-0.1.0.dist-info/RECORD
